market_maker/__init__.py
market_maker/_settings_base.py
market_maker/bitmex.py
market_maker/custom_strategy.py
market_maker/market_maker.py
market_maker/settings.py
market_maker/auth/APIKeyAuth.py
market_maker/auth/APIKeyAuthWithExpires.py
market_maker/auth/AccessTokenAuth.py
market_maker/auth/__init__.py
market_maker/utils/__init__.py
market_maker/utils/constants.py
market_maker/utils/dotdict.py
market_maker/utils/errors.py
market_maker/utils/log.py
market_maker/utils/math.py
market_maker/ws/__init__.py
market_maker/ws/ws_thread.py
bitmex_market_maker-1.6.1.dist-info/LICENSE
bitmex_market_maker-1.6.1.dist-info/METADATA
bitmex_market_maker-1.6.1.dist-info/WHEEL
bitmex_market_maker-1.6.1.dist-info/entry_points.txt
bitmex_market_maker-1.6.1.dist-info/top_level.txt
bitmex_market_maker-1.6.1.dist-info/RECORD
