Metadata-Version: 2.1
Name: bitmex-market-maker
Version: 1.6.1
Summary: Market making bot for BitMEX API
Home-page: https://github.com/BitMEX/sample-market-maker
Author: Samuel Reed
Author-email: sam@bitmex.com
License-File: LICENSE
Requires-Dist: requests
Requires-Dist: websocket-client
Requires-Dist: future
